tests/__init__.py
tests/test_data.py
txquant/__init__.py
txquant/data.py
txquant-0.1.0.dist-info/METADATA
txquant-0.1.0.dist-info/WHEEL
txquant-0.1.0.dist-info/top_level.txt
txquant-0.1.0.dist-info/RECORD
