Metadata-Version: 2.4
Name: txquant
Version: 0.1.0
Summary: 天行量化，一个量化回测框架
Home-page: https://github.com/95ge/txquant
Author: 95ge
Author-email: 445646258@qq.com
Classifier: Programming Language :: Python :: 3
Classifier: License :: OSI Approved :: MIT License
Classifier: Operating System :: OS Independent
Requires-Python: >=3.0
Requires-Dist: LTtx
Requires-Dist: pyzmq
Requires-Dist: requests
Requires-Dist: pandas
Requires-Dist: pandas_market_calendars
Requires-Dist: cnlunar
Dynamic: author
Dynamic: author-email
Dynamic: classifier
Dynamic: description
Dynamic: description-content-type
Dynamic: home-page
Dynamic: requires-dist
Dynamic: requires-python
Dynamic: summary
